ChangeLogs.rst
LICENSE
MANIFEST.in
README.rst
setup.py
conf/dnscherry.ini
dnscherry/__init__.py
dnscherry.egg-info/PKG-INFO
dnscherry.egg-info/SOURCES.txt
dnscherry.egg-info/dependency_links.txt
dnscherry.egg-info/not-zip-safe
dnscherry.egg-info/requires.txt
dnscherry.egg-info/top_level.txt
dnscherry/auth/__init__.py
dnscherry/auth/modHtpasswd.py
dnscherry/auth/modLdap.py
dnscherry/auth/modNone.py
docs/Makefile
docs/README.rst
docs/auth_module.rst
docs/changelog.rst
docs/conf.py
docs/deploy.rst
docs/index.rst
docs/install.rst
docs/make.bat
docs/assets/basic.css
docs/assets/cherrypy.jpg
docs/assets/cherrypy.png
docs/assets/favicon.png
docs/assets/logo.png
docs/assets/main_screen.png
docs/assets/nature.css
docs/assets/pygments.css
docs/assets/python-logo.png
docs/assets/python-powered.png
goodies/apache.conf
goodies/init-debian
goodies/lighttpd.conf
goodies/nginx.conf
resources/static/css/bootstrap-theme.css
resources/static/css/bootstrap-theme.min.css
resources/static/css/bootstrap.css
resources/static/css/bootstrap.min.css
resources/static/css/custom.css
resources/static/css/style.css
resources/static/css/tablesorter-bootstrap.css
resources/static/fonts/glyphicons-halflings-regular.eot
resources/static/fonts/glyphicons-halflings-regular.svg
resources/static/fonts/glyphicons-halflings-regular.ttf
resources/static/fonts/glyphicons-halflings-regular.woff
resources/static/img/apple-touch-icon-114-precomposed.png
resources/static/img/apple-touch-icon-144-precomposed.png
resources/static/img/apple-touch-icon-57-precomposed.png
resources/static/img/apple-touch-icon-72-precomposed.png
resources/static/img/favicon.png
resources/static/img/glyphicons-halflings-white.png
resources/static/img/glyphicons-halflings.png
resources/static/js/bootstrap-notify.js
resources/static/js/bootstrap.min.js
resources/static/js/html5shiv.js
resources/static/js/jquery.min.js
resources/static/js/jquery.tablesorter.min.js
resources/static/js/less-1.3.3.min.js
resources/static/js/scripts.js
resources/static/less/alerts.less
resources/static/less/badges.less
resources/static/less/bootstrap.less
resources/static/less/breadcrumbs.less
resources/static/less/button-groups.less
