Metadata-Version: 1.1
Name: dnscherry
Version: 0.1.3
Summary: A simple web application to manage DNS zones
Home-page: https://github.com/kakwa/dnscherry
Author: Pierre-Francois Carpentier
Author-email: carpentier.pf@gmail.com
License: The MIT License (MIT)
